MANIFEST.in
README.md
setup.py
myraptor/__init__.py
myraptor/__main__.py
myraptor/__version__.py
myraptor/classes.py
myraptor/create_tb.py
myraptor/helpers.py
myraptor/mr.py
myraptor/raptor.py
myraptor.egg-info/PKG-INFO
myraptor.egg-info/SOURCES.txt
myraptor.egg-info/dependency_links.txt
myraptor.egg-info/requires.txt
myraptor.egg-info/top_level.txt
myraptor/data/data.csv
myraptor/data/data_stops.csv